cl_sii/__init__.py
cl_sii/py.typed
cl_sii/base/__init__.py
cl_sii/base/constants.py
cl_sii/contribuyente/__init__.py
cl_sii/contribuyente/constants.py
cl_sii/cte/__init__.py
cl_sii/cte/data_models.py
cl_sii/cte/parsers.py
cl_sii/cte/f29/__init__.py
cl_sii/cte/f29/data_models.py
cl_sii/cte/f29/parse_datos_obj.py
cl_sii/data/cte/f29_datos_obj_missing_key_fixes.json
cl_sii/data/cte/schemas-json/f29_datos_obj.schema.json
cl_sii/data/ref/factura_electronica/schemas-xml/AEC_v10.xsd
cl_sii/data/ref/factura_electronica/schemas-xml/Cesion_v10.xsd
cl_sii/data/ref/factura_electronica/schemas-xml/DTECedido_v10.xsd
cl_sii/data/ref/factura_electronica/schemas-xml/DTE_v10.xsd
cl_sii/data/ref/factura_electronica/schemas-xml/EnvioDTE_v10.xsd
cl_sii/data/ref/factura_electronica/schemas-xml/LceCal_v10.xsd
cl_sii/data/ref/factura_electronica/schemas-xml/LceCoCertif_v10.xsd
cl_sii/data/ref/factura_electronica/schemas-xml/LceSiiTypes_v10.xsd
cl_sii/data/ref/factura_electronica/schemas-xml/LibroCV_v10.xsd
cl_sii/data/ref/factura_electronica/schemas-xml/Recibos_v10.xsd
cl_sii/data/ref/factura_electronica/schemas-xml/SiiTypes_v10.xsd
cl_sii/data/ref/factura_electronica/schemas-xml/xmldsignature_v10.xsd
cl_sii/dte/__init__.py
cl_sii/dte/constants.py
cl_sii/dte/data_models.py
cl_sii/dte/parse.py
cl_sii/extras/__init__.py
cl_sii/extras/dj_filters.py
cl_sii/extras/dj_form_fields.py
cl_sii/extras/dj_model_fields.py
cl_sii/extras/dj_url_converters.py
cl_sii/extras/drf_fields.py
cl_sii/extras/drf_serializers.py
cl_sii/extras/mm_fields.py
cl_sii/extras/pydantic_types.py
cl_sii/libs/__init__.py
cl_sii/libs/crypto_utils.py
cl_sii/libs/csv_utils.py
cl_sii/libs/dataclass_utils.py
cl_sii/libs/encoding_utils.py
cl_sii/libs/io_utils.py
cl_sii/libs/json_utils.py
cl_sii/libs/mm_utils.py
cl_sii/libs/rows_processing.py
cl_sii/libs/tz_utils.py
cl_sii/libs/xml_utils.py
cl_sii/rcv/__init__.py
cl_sii/rcv/constants.py
cl_sii/rcv/data_models.py
cl_sii/rcv/parse_csv.py
cl_sii/rtc/__init__.py
cl_sii/rtc/constants.py
cl_sii-0.70.0.dist-info/licenses/LICENSE
cl_sii-0.70.0.dist-info/METADATA
cl_sii-0.70.0.dist-info/WHEEL
cl_sii-0.70.0.dist-info/top_level.txt
cl_sii-0.70.0.dist-info/RECORD
