Metadata-Version: 2.4
Name: cl-sii
Version: 0.70.0
Summary: Python library for Servicio de Impuestos Internos (SII) of Chile.
Author-email: Fyntex TI SpA <no-reply@fyntex.ai>
License-Expression: MIT
Project-URL: Homepage, https://github.com/fyntex/lib-cl-sii-python
Project-URL: Changelog, https://github.com/fyntex/lib-cl-sii-python/blob/develop/HISTORY.md
Classifier: Development Status :: 3 - Alpha
Classifier: Intended Audience :: Developers
Classifier: Natural Language :: English
Classifier: Programming Language :: Python :: 3
Classifier: Programming Language :: Python :: 3.9
Classifier: Programming Language :: Python :: 3.10
Classifier: Programming Language :: Python :: 3.11
Classifier: Programming Language :: Python :: 3.12
Classifier: Programming Language :: Python :: 3.13
Requires-Python: <3.14,>=3.9
License-File: LICENSE
Requires-Dist: cryptography>=43.0.0
Requires-Dist: defusedxml<1,>=0.6.0
Requires-Dist: jsonschema>=3.1.1
Requires-Dist: lxml<7,>=5.2.1
Requires-Dist: marshmallow<5,>=4
Requires-Dist: pydantic!=1.7.*,!=1.8.*,!=1.9.*,>=2.10.0
Requires-Dist: pyOpenSSL>=24.0.0
Requires-Dist: pytz>=2019.3
Requires-Dist: signxml>=4.0.0
Requires-Dist: typing-extensions>=4.0.1
Provides-Extra: django
Requires-Dist: Django>=4.2; extra == "django"
Provides-Extra: django-filter
Requires-Dist: django-filter>=24.2; extra == "django-filter"
Provides-Extra: djangorestframework
Requires-Dist: djangorestframework<3.17,>=3.10.3; extra == "djangorestframework"
Provides-Extra: pydantic
Requires-Dist: pydantic>=2.0; extra == "pydantic"
Dynamic: license-file
